{
  "generated_at": "2026-07-20T21:54:16.254Z",
  "repos": [
    {
      "key": "helpdesk-hub",
      "name": "HelpDesk Hub",
      "url": "https://github.com/izumacha/helpdesk-hub",
      "ci": {
        "status": "success",
        "run_url": "https://github.com/izumacha/helpdesk-hub/actions/runs/29781703365",
        "branch": "main"
      },
      "last_commit": {
        "iso": "2026-07-20T21:50:08Z",
        "sha7": "7b217a3",
        "url": "https://github.com/izumacha/helpdesk-hub/commit/7b217a36afbabc67e5550e930f873d7b3fd14250"
      },
      "languages": [
        "TypeScript",
        "Shell",
        "JavaScript",
        "Dockerfile",
        "CSS"
      ],
      "test_file_count": 145,
      "stale": false
    },
    {
      "key": "incident-insight",
      "name": "IncidentInsight",
      "url": "https://github.com/izumacha/incident-insight",
      "ci": {
        "status": "success",
        "run_url": "https://github.com/izumacha/incident-insight/actions/runs/29743415542",
        "branch": "main"
      },
      "last_commit": {
        "iso": "2026-07-20T12:45:12Z",
        "sha7": "64427aa",
        "url": "https://github.com/izumacha/incident-insight/commit/64427aae35a9f463413c00a948b93a6ae625d210"
      },
      "languages": [
        "C#",
        "HTML",
        "CSS",
        "TypeScript",
        "Shell",
        "Dockerfile"
      ],
      "test_file_count": 31,
      "stale": false
    },
    {
      "key": "AI-Docker-Environment",
      "name": "AI-Docker-Environment",
      "url": "https://github.com/izumacha/AI-Docker-Environment",
      "ci": {
        "status": "skipped",
        "run_url": "https://github.com/izumacha/AI-Docker-Environment/actions/runs/29781537125",
        "branch": "main"
      },
      "last_commit": {
        "iso": "2026-07-20T21:46:06Z",
        "sha7": "5a04ffa",
        "url": "https://github.com/izumacha/AI-Docker-Environment/commit/5a04ffaa1f1f0e3460b4e0964f714cfac4545466"
      },
      "languages": [
        "Shell",
        "Dockerfile"
      ],
      "test_file_count": 2,
      "stale": false
    },
    {
      "key": "profile-portfolio",
      "name": "profile-portfolio",
      "url": "https://github.com/izumacha/profile-portfolio",
      "ci": {
        "status": "success",
        "run_url": "https://github.com/izumacha/profile-portfolio/actions/runs/29781458261",
        "branch": "main"
      },
      "last_commit": {
        "iso": "2026-07-20T21:46:09Z",
        "sha7": "738a1fa",
        "url": "https://github.com/izumacha/profile-portfolio/commit/738a1fa2649b82956005762fa4565a5df818336c"
      },
      "languages": [
        "HTML",
        "TypeScript"
      ],
      "test_file_count": 3,
      "stale": false
    }
  ],
  "site_quality": {
    "lighthouse": null,
    "visual_regression": null,
    "links": null,
    "html_validate": null
  }
}
